mcp_time_server_studio-0.1.1.dist-info/licenses/LICENSE
time_server_pkg/__init__.py
time_server_pkg/main.py
time_server_pkg/py.typed
mcp_time_server_studio-0.1.1.dist-info/METADATA
mcp_time_server_studio-0.1.1.dist-info/WHEEL
mcp_time_server_studio-0.1.1.dist-info/entry_points.txt
mcp_time_server_studio-0.1.1.dist-info/top_level.txt
mcp_time_server_studio-0.1.1.dist-info/RECORD
