Metadata-Version: 2.4
Name: mcp-time-server-studio
Version: 0.1.1
Summary: 基于 Model Context Protocol (MCP) 的时间服务器，支持通过 StreamableHTTP 传输协议提供当前时间查询服务
Home-page: https://github.com/yourusername/mcp-time-server-studio
Author: Your Name
Author-email: Your Name <your.email@example.com>
License: MIT License
Keywords: time-server,mcp,json-rpc,fastapi,timezone,streamable-http
Classifier: Programming Language :: Python :: 3
Classifier: License :: OSI Approved :: MIT License
Classifier: Operating System :: OS Independent
Classifier: Framework :: FastAPI
Classifier: Topic :: Internet :: WWW/HTTP :: HTTP Servers
Requires-Python: >=3.7
License-File: LICENSE
Requires-Dist: mcp>=0.1.0
Requires-Dist: fastapi>=0.100.0
Requires-Dist: uvicorn>=0.22.0
Requires-Dist: pytz>=2023.3
Requires-Dist: anyio>=3.0.0
Dynamic: author
Dynamic: home-page
Dynamic: license-file
Dynamic: requires-python
